{
  "navigation": [
    { "path": "home", "name": "Home" },
    { "path": "about", "name": "About" },
    { "path": "products", "name": "Products" }
  ],

  "social": [
    { "imgPath": "assets/icons/facebook.svg", "imgAlt": "Facebook Icon" },
    { "imgPath": "assets/icons/instagram.svg", "imgAlt": "Instagram Icon" },
    { "imgPath": "assets/icons/twitter.svg", "imgAlt": "Twitter Icon" }
  ],

  "content": [
    {
      "pageName": "home",
      "content": "<section class='homeSection'> <div class='homeSection__hero'> <h1 class='homeSection__hero__heading'>The Benjamin Store</h1> <p class='homeSection__hero__paragraph'> Lorem ipsum dolor sit amet, consectetur adipisicing elit. </p> <a href='#' class='btn btn--white homeSection__hero__button'> SEE THE GOODS </a> </div> <div class='homeSection__about'> <h1 class='homeSection__about__heading'>ABOUT</h1> <p class='homeSection__about__paragraph'> Lorem ipsum dolor, sit amet consectetur adipisicing elit. Perspiciatis maxime eum mollitia dolorem ratione ab sint sequi repellendus sapiente eveniet assumenda consectetur earum nulla animi dolore eaque nam, cupiditate commodi ex obcaecati amet nobis nemo autem! Tenetur temporibus debitis incidunt aperiam, suscipit accusamus ipsum et pariatur harum maiores repellendus, commodi ducimus, eligendi eveniet ab aspernatur quidem minus? Illum neque illo assumenda dolorem officiis, incidunt, ratione cumque tempore aspernatur dolore eos. </p> <div class='homeSection__about__buttons'> <a href='#' class='btn btn--blue'>KNOW MORE</a> <a href='#' class='btn btn--black'>SEE THE GOODS</a> </div> </div> <div class='homeSection__goals'> <h1 class='homeSection__goals__heading'>OUR GOALS</h1> <div class='homeSection__cardsSection'> <div class='homeSection__cardsSection__card'> <i> <p class='homeSection__cardsSection__paragraph'> 'Lorem ipsum dolor sit amet consectetur adipisicing elit. Saepe nemo voluptatem architecto inventore accusamus rerum perferendis esse quos voluptates! Assumenda!' </p> </i> </div> <div class='homeSection__cardsSection__card'> <i> <p class='homeSection__cardsSection__paragraph'> 'Lorem ipsum dolor sit amet consectetur adipisicing elit. Itaque sint laboriosam nostrum enim delectus ullam minima! Officiis quis atque minima?' </p> </i> </div> <div class='homeSection__cardsSection__card'> <i> <p class='homeSection__cardsSection__paragraph'> 'Lorem ipsum dolor sit amet consectetur adipisicing elit. Recusandae illo facere pariatur. Temporibus obcaecati praesentium, nesciunt natus eius numquam a.' </p> </i> </div> </div> </div> <footer class='footerSection'> <div class='footerSection__container'> <h1 class='footerSection__heading'>social</h1> <p class='footerSection__paragraph'>Facebook</p> <p class='footerSection__paragraph'>Twitter</p> </div> <div class='footerSection__container'> <h1 class='footerSection__heading'>legal</h1> <p class='footerSection__paragraph'>Privacy Policy</p> <p class='footerSection__paragraph'>Terms of Use</p> </div> <div class='footerSection__container'> <h1 class='footerSection__heading'>company</h1> <p class='footerSection__paragraph'>The Benjamin Blog</p> <p class='footerSection__paragraph'>Security</p> </div> <div class='footerSection__mailing'> <h1 class='footerSection__heading'> subscribe to our mailing list </h1> <input type='email' placeholder='Your Email' /> <a href='#' class='btn btn--white'>SUBSCRIBE →</a> </div> </footer> </section>"
    },
    {
      "pageName": "about",
      "content": "<section class='aboutSection'> <div class='aboutSection__about'> <h1 class='aboutSection__about__heading'>ABOUT</h1> <p class='aboutSection__about__paragraph'> Lorem ipsum dolor sit amet consectetur adipisicing elit. Accusamus, architecto. Cupiditate harum perspiciatis voluptates assumenda repellat quidem! Reiciendis, pariatur, porro hic recusandae eum ullam laborum facilis dolorum aut magni officia. Libero facilis ea dolor ducimus nam voluptatem aspernatur, molestiae cupiditate? </p> <p class='aboutSection__about__paragraph'> Lorem ipsum dolor sit amet consectetur adipisicing elit. Consequuntur itaque aperiam est minima suscipit, nisi iusto voluptatum veniam laboriosam obcaecati nostrum incidunt, vero nam quam? Veniam minus similique quisquam ex delectus et aperiam esse architecto harum recusandae non rem, modi neque natus consectetur voluptatibus, cupiditate numquam, temporibus magnam doloremque aliquam facere asperiores assumenda. Perferendis, ea repellat esse molestias reprehenderit perspiciatis! </p> <p class='aboutSection__about__paragraph'> Lorem ipsum dolor sit amet consectetur adipisicing elit. Ducimus tempora iste quo ut magnam quam animi nulla voluptatum tempore sapiente, perspiciatis dignissimos soluta provident culpa laboriosam non voluptatem voluptate dolore! </p> </div> <div class='aboutSection__people'> <h1 class='aboutSection__people__heading'>MEET THE PEOPLE</h1> <div class='aboutSection__people__container'> <img class='aboutSection__people__image' src='assets/man-01.jpg' alt='man' /> <img class='aboutSection__people__image' src='assets/woman-01.jpg' alt='woman' /> <img class='aboutSection__people__image' src='assets/woman-02.jpg' alt='woman' /> <img class='aboutSection__people__image' src='assets/woman-03.jpg' alt='woman' /> <a href='#' class='btn btn--blue'> AND MORE → </a> </div> </div> <div class='aboutSection__satisfied'> <h1 class='aboutSection__satisfied__heading'>SATISFIED CUSTOMERS</h1> <p class='aboutSection__satisfied__paragraph'> <i> Lorem ipsum dolor sit amet consectetur adipisicing elit. Nobis aut necessitatibus porro nulla distinctio cupiditate maiores at ut amet magni vel, delectus dignissimos. Excepturi fugiat culpa amet ex magni iusto tempore, dolores ab? Sed, eos minus praesentium dolor magni non! </i> <br /><span>-Jack Hammer</span> </p> <p class='aboutSection__satisfied__paragraph'> <i> Lorem ipsum dolor sit amet, consectetur adipisicing elit. Placeat quod provident esse expedita nemo ea, numquam perspiciatis iusto in voluptate quisquam, quam deleniti iste sunt quo ducimus obcaecati officia unde ad fugiat eius tempore. Dolore neque ducimus ab necessitatibus odit. </i> <br /><span>-Hannah Williams</span> </p> <p class='aboutSection__satisfied__paragraph'> <i> Lorem ipsum dolor sit amet consectetur adipisicing elit. Illo laudantium consequatur reprehenderit neque, eligendi tenetur, ipsum ullam minus illum sint eum magni ut, ab sunt ea numquam quae rem obcaecati. Quidem eum eius dicta temporibus aspernatur quis id consequuntur fuga. </i> <br /><span>-Brit Jones</span> </p> </div> <footer class='footerSection'> <div class='footerSection__container'> <h1 class='footerSection__heading'>social</h1> <p class='footerSection__paragraph'>Facebook</p> <p class='footerSection__paragraph'>Twitter</p> </div> <div class='footerSection__container'> <h1 class='footerSection__heading'>legal</h1> <p class='footerSection__paragraph'>Privacy Policy</p> <p class='footerSection__paragraph'>Terms of Use</p> </div> <div class='footerSection__container'> <h1 class='footerSection__heading'>company</h1> <p class='footerSection__paragraph'>The Benjamin Blog</p> <p class='footerSection__paragraph'>Security</p> </div> <div class='footerSection__mailing'> <h1 class='footerSection__heading'> subscribe to our mailing list </h1> <input type='email' placeholder='Your Email' /> <a href='#' class='btn btn--white'>SUBSCRIBE →</a> </div> </footer> </section>"
    },
    {
      "pageName": "products",
      "content": "<section class='productsSection'> <div class='productsSection__quality'> <h1 class='productsSection__quality__heading'>PRODUCT QUALITY</h1> <p class='productsSection__quality__paragraph'> Lorem, ipsum dolor sit amet consectetur adipisicing elit. Quas, laudantium obcaecati illo autem architecto explicabo harum optio facere soluta, praesentium id sed magni nesciunt officia ab voluptatibus, vel provident? Dicta sed, officiis sapiente a quae reprehenderit cumque fugit repudiandae, numquam, nisi natus asperiores architecto cum ducimus! Cum minima quam consequatur. </p> <p class='productsSection__quality__paragraph'> Lorem ipsum dolor sit amet consectetur, adipisicing elit. Error ad optio ipsa vel corporis accusantium? Cupiditate officiis culpa aut totam, nam similique non magnam ipsam dolor soluta error, tempore aperiam mollitia earum quia iusto iure rerum eaque, ratione fugit? Doloremque dolore magni tempore aut quas! Excepturi explicabo, cumque laborum blanditiis quod similique, ab quae corporis labore ipsa velit ex fuga rem minus distinctio, officia tempora doloremque quam sint saepe unde. Fuga facere dolores optio corrupti ea animi laudantium nihil earum culpa rerum dolorum consequuntur excepturi asperiores, quisquam minima porro mollitia quibusdam eaque ipsum repudiandae molestiae, cumque nesciunt totam officiis? Officia? </p> </div> <div class='productsSection__products'> <h1 class='productsSection__products__heading'>OUR PRODUCTS</h1> <div class='productsSection__products__container'> <div class='productsSection__products__card productsSection__products__card--01' > <h1 class='productsSection__products__card__heading'>NINTENDO</h1> </div> <div class='productsSection__products__card productsSection__products__card--02' > <h1 class='productsSection__products__card__heading'>PS2</h1> </div> <div class='productsSection__products__card productsSection__products__card--03' > <h1 class='productsSection__products__card__heading'>XBOX</h1> </div> </div> </div> <div class='productsSection__otherP'> <h1 class='productsSection__otherP__heading'> OTHER PRODUCTS </h1> <div class='productsSection__otherP__container'> <div class='productsSection__otherP__card productsSection__otherP__card--01' > <h1 class='productsSection__otherP__card__heading'>IPHONE XS</h1> </div> <div class='productsSection__otherP__card productsSection__otherP__card--02' > <h1 class='productsSection__otherP__card__heading'>TELEVISION</h1> </div> <div class='productsSection__otherP__card productsSection__otherP__card--03' > <h1 class='productsSection__otherP__card__heading'>LAPTOP</h1> </div> </div> </div> <footer class='footerSection'> <div class='footerSection__container'> <h1 class='footerSection__heading'>social</h1> <p class='footerSection__paragraph'>Facebook</p> <p class='footerSection__paragraph'>Twitter</p> </div> <div class='footerSection__container'> <h1 class='footerSection__heading'>legal</h1> <p class='footerSection__paragraph'>Privacy Policy</p> <p class='footerSection__paragraph'>Terms of Use</p> </div> <div class='footerSection__container'> <h1 class='footerSection__heading'>company</h1> <p class='footerSection__paragraph'>The Benjamin Blog</p> <p class='footerSection__paragraph'>Security</p> </div> <div class='footerSection__mailing'> <h1 class='footerSection__heading'> subscribe to our mailing list </h1> <input type='email' placeholder='Your Email' /> <a href='#' class='btn btn--white'>SUBSCRIBE →</a> </div> </footer> </section>"
    }
  ]
}
